{
    "id": "https://edsilv.github.io/test-manifests/pres3-collection.json",
    "type": "Collection",
    "members": [
        {
            "id": "https://edsilv.github.io/test-manifests/pres3-3d.json",
            "type": "Manifest",
            "label": "3D"
        },
        {
            "id": "https://edsilv.github.io/test-manifests/pres3-pdf.json",
            "type": "Manifest",
            "label": "PDF"
        },
        {
            "id": "https://edsilv.github.io/test-manifests/pres3-video.json",
            "type": "Manifest",
            "label": "Video"
        }
    ]
}